{
  "__inputs": [
    {
      "name": "DS_QUESTDB-LOCAL",
      "label": "questdb-local",
      "description": "",
      "type": "datasource",
      "pluginId": "questdb-questdb-datasource",
      "pluginName": "QuestDB"
    }
  ],
  "__elements": {},
  "__requires": [
    {
      "type": "panel",
      "id": "geomap",
      "name": "Geomap",
      "version": ""
    },
    {
      "type": "grafana",
      "id": "grafana",
      "name": "Grafana",
      "version": "12.0.1"
    },
    {
      "type": "datasource",
      "id": "questdb-questdb-datasource",
      "name": "QuestDB",
      "version": "0.1.5"
    }
  ],
  "annotations": {
    "list": [
      {
        "builtIn": 1,
        "datasource": {
          "type": "grafana",
          "uid": "-- Grafana --"
        },
        "enable": true,
        "hide": true,
        "iconColor": "rgba(0, 211, 255, 1)",
        "name": "Annotations & Alerts",
        "type": "dashboard"
      }
    ]
  },
  "editable": true,
  "fiscalYearStartMonth": 0,
  "graphTooltip": 0,
  "id": null,
  "links": [],
  "panels": [
    {
      "datasource": {
        "type": "questdb-questdb-datasource",
        "uid": "${DS_QUESTDB-LOCAL}"
      },
      "fieldConfig": {
        "defaults": {
          "color": {
            "mode": "thresholds"
          },
          "custom": {
            "hideFrom": {
              "legend": false,
              "tooltip": false,
              "viz": false
            }
          },
          "links": [
            {
              "targetBlank": true,
              "title": "Wykres",
              "url": "http://192.168.1.62:3000/public-dashboards/72c5c128360e4da0bafe83b9f2326192?var-sensor_id=${__data.fields.Lokalizacja}"
            }
          ],
          "mappings": [],
          "thresholds": {
            "mode": "percentage",
            "steps": [
              {
                "color": "green"
              }
            ]
          }
        },
        "overrides": [
          {
            "matcher": {
              "id": "byName",
              "options": "Temperatura"
            },
            "properties": [
              {
                "id": "unit",
                "value": "celsius"
              }
            ]
          },
          {
            "matcher": {
              "id": "byName",
              "options": "Wilgotność"
            },
            "properties": [
              {
                "id": "unit",
                "value": "percent"
              }
            ]
          }
        ]
      },
      "gridPos": {
        "h": 20,
        "w": 24,
        "x": 0,
        "y": 0
      },
      "id": 1,
      "options": {
        "basemap": {
          "config": {},
          "name": "Layer 0",
          "tooltip": false,
          "type": "osm-standard"
        },
        "controls": {
          "mouseWheelZoom": true,
          "showAttribution": true,
          "showDebug": false,
          "showMeasure": false,
          "showScale": false,
          "showZoom": true
        },
        "layers": [
          {
            "config": {
              "showLegend": false,
              "style": {
                "color": {
                  "fixed": "dark-green"
                },
                "opacity": 0.4,
                "rotation": {
                  "fixed": 0,
                  "max": 360,
                  "min": -360,
                  "mode": "mod"
                },
                "size": {
                  "fixed": 10,
                  "max": 15,
                  "min": 2
                },
                "symbol": {
                  "fixed": "img/icons/marker/circle.svg",
                  "mode": "fixed"
                },
                "symbolAlign": {
                  "horizontal": "center",
                  "vertical": "center"
                },
                "text": {
                  "fixed": "",
                  "mode": "fixed"
                },
                "textConfig": {
                  "fontSize": 12,
                  "offsetX": 0,
                  "offsetY": 0,
                  "textAlign": "center",
                  "textBaseline": "middle"
                }
              }
            },
            "location": {
              "mode": "auto"
            },
            "name": "Czujniki",
            "tooltip": true,
            "type": "markers"
          }
        ],
        "tooltip": {
          "mode": "details"
        },
        "view": {
          "allLayers": true,
          "id": "coords",
          "lat": 50.575396,
          "lon": 16.672255,
          "zoom": 13.79
        }
      },
      "pluginVersion": "12.0.1",
      "targets": [
        {
          "builderOptions": "The query can't be parsed.",
          "datasource": {
            "type": "questdb-questdb-datasource",
            "uid": "${DS_QUESTDB-LOCAL}"
          },
          "format": 1,
          "meta": {
            "builderOptions": "The query can't be parsed."
          },
          "queryType": "sql",
          "rawSql": "SELECT sensors.id, sensors.timestamp, config.location, config.description, config.lat, config.lon, sensors.temperature, sensors.humidity, sensors.pm25, sensors.pm10 FROM sensors INNER JOIN config on sensors.id=config.id",
          "refId": "A",
          "selectedFormat": 2
        }
      ],
      "title": "Mapa",
      "transformations": [
        {
          "id": "organize",
          "options": {
            "excludeByName": {
              "id": true,
              "lat": false,
              "lon": false
            },
            "includeByName": {},
            "indexByName": {},
            "renameByName": {
              "description": "Opis",
              "humidity": "Wilgotność",
              "id": "",
              "lat": "Szer. geograficzna",
              "location": "Lokalizacja",
              "lon": "Dł. geograficzna",
              "pm1": "PM1",
              "pm10": "PM10",
              "pm25": "PM2.5",
              "temperature": "Temperatura",
              "timestamp": "Czas aktualizacji"
            }
          }
        }
      ],
      "type": "geomap"
    }
  ],
  "schemaVersion": 41,
  "tags": [],
  "templating": {
    "list": []
  },
  "time": {
    "from": "now-1h",
    "to": "now"
  },
  "timepicker": {},
  "timezone": "browser",
  "title": "Mapa",
  "uid": "43f7140b-031c-4458-ad63-2beec16bd20e",
  "version": 39,
  "weekStart": ""
}